ribbon/__init__.py
ribbon/cypher_utils.py
ribbon/exceptions.py
ribbon/graph.py
ribbon/node_model.py
ribbon/parsing.py
ribbon/py2neo_additions.py
ribbon/settings.py
ribbon_graph-0.1.1.dist-info/DESCRIPTION.rst
ribbon_graph-0.1.1.dist-info/METADATA
ribbon_graph-0.1.1.dist-info/RECORD
ribbon_graph-0.1.1.dist-info/WHEEL
ribbon_graph-0.1.1.dist-info/metadata.json
ribbon_graph-0.1.1.dist-info/top_level.txt
