Metadata-Version: 2.0
Name: ribbon-graph
Version: 0.1.1
Summary: A Declarative Graph API Django App
Home-page: https://github.com/TheArtOfEngineering/RibbonGraph
Author: Tyler F Cloutier
Author-email: cloutiertyler@aol.com
License: MIT
Platform: UNKNOWN
Classifier: Environment :: Web Environment
Classifier: Framework :: Django
Classifier: Intended Audience :: Developers
Classifier: License :: OSI Approved :: MIT License
Classifier: Operating System :: OS Independent
Classifier: Programming Language :: Python
Classifier: Programming Language :: Python :: 2.7
Classifier: Topic :: Internet :: WWW/HTTP
Classifier: Topic :: Internet :: WWW/HTTP :: Dynamic Content
Requires-Dist: djangorestframework
Requires-Dist: py2neo
